{
    "revision": [
        514,
        510
    ],
    "assetBundleList": [
        {
            "id": 43817,
            "name": "sud_vo_cmn_yu-05-link-00_evolution-01",
            "size": 11221,
            "crc": 635614108,
            "state": "UPDATE",
            "md5": "e248cae43b6293de3d618b7c987ecfb9",
            "objectName": "iTDoZi",
            "generation": "1747818458367566",
            "uploadVersionId": 202050
        },
        {
            "id": 43818,
            "name": "sud_vo_cmn_yu-05-link-00_b_gacha-get",
            "size": 25290,
            "crc": 4224971619,
            "state": "UPDATE",
            "md5": "03cff5fb6936474ce0c28604291d4d79",
            "objectName": "KL5RK5",
            "generation": "1748409195002592",
            "uploadVersionId": 202050
        },
        {
            "id": 43835,
            "name": "sud_vo_cmn_yu-05-link-00_evolution-02",
            "size": 19509,
            "crc": 3508151817,
            "state": "UPDATE",
            "md5": "7c5abd8d0d5ef4c32af45decafa825ee",
            "objectName": "dUtiW8",
            "generation": "1747818458351026",
            "uploadVersionId": 202050
        },
        {
            "id": 44148,
            "name": "img_gacha_button_free-25-0608",
            "size": 36286,
            "crc": 1970902568,
            "state": "UPDATE",
            "md5": "9e484b713e0dafb4898e6f9f067ad961",
            "objectName": "62qDDx",
            "generation": "1748629124607995",
            "uploadVersionId": 202050
        },
        {
            "id": 44149,
            "name": "img_banner_s_gacha-free-25-0608",
            "size": 39432,
            "crc": 469953424,
            "state": "UPDATE",
            "md5": "35110eb8056a2bc072fba16b3da2722c",
            "objectName": "xxWVJa",
            "generation": "1748629124676934",
            "uploadVersionId": 202050
        },
        {
            "id": 44150,
            "name": "img_gacha_screen_free-25-0608",
            "size": 323223,
            "crc": 3313370444,
            "state": "UPDATE",
            "md5": "ecc3de65aa4d0665b7573243ac897022",
            "objectName": "Qhk7to",
            "generation": "1748629124754398",
            "uploadVersionId": 202050
        },
        {
            "id": 44151,
            "name": "img_banner_l_gacha-free-25-0608",
            "size": 85737,
            "crc": 3731431895,
            "state": "UPDATE",
            "md5": "5b5d9c1bc5601c8f79e96a0d7f39c6e2",
            "objectName": "p18yoA",
            "generation": "1748629124653773",
            "uploadVersionId": 202050
        },
        {
            "id": 44152,
            "name": "img_gacha_appeal_free-25-0608",
            "size": 18916,
            "crc": 105080489,
            "state": "UPDATE",
            "md5": "85f7bc10ef7c8f9c06237691f75cf955",
            "objectName": "XberZK",
            "generation": "1748629124582427",
            "uploadVersionId": 202050
        }
    ],
    "resourceList": [
        {
            "id": 1839,
            "name": "story-character-relations.json",
            "size": 204277,
            "state": "UPDATE",
            "md5": "e19138e171dc1a380d0b103839f01968",
            "objectName": "iVKnyF",
            "generation": "1749019770062914",
            "uploadVersionId": 202050
        }
    ],
    "urlFormat": "https://d2ilil7yh5oi1v.cloudfront.net/solis-{v}-{type}/{o}?generation={g}&alt=media"
}