{
    "revision": [
        548,
        545
    ],
    "assetBundleList": [
        {
            "id": 44715,
            "name": "img_shop_thumb_shop-pack-25-0625-02",
            "size": 192246,
            "crc": 3147295436,
            "state": "UPDATE",
            "md5": "56a6fc582a3f3dded4fb2c883a5015b6",
            "objectName": "amcTU3",
            "generation": "1751126749361481",
            "uploadVersionId": 202050
        },
        {
            "id": 44943,
            "name": "img_banner_l_event-xmas-mission-25-0702",
            "size": 82621,
            "crc": 2773862624,
            "state": "UPDATE",
            "md5": "cc3e9a6cc00a9b29e6969311420936f8",
            "objectName": "ITnz82",
            "generation": "1750937417170468",
            "uploadVersionId": 202050
        }
    ],
    "resourceList": [
        {
            "id": 1839,
            "name": "story-character-relations.json",
            "size": 207564,
            "state": "UPDATE",
            "md5": "18df229966032c4fcb1f9dc7fb147cc1",
            "objectName": "iVKnyF",
            "generation": "1751248173379767",
            "uploadVersionId": 202050
        }
    ],
    "urlFormat": "https://d2ilil7yh5oi1v.cloudfront.net/solis-{v}-{type}/{o}?generation={g}&alt=media"
}