{
    "revision": [
        571,
        570
    ],
    "assetBundleList": [
        {
            "id": 45557,
            "name": "img_dokan_free_login-pack-01-changed",
            "size": 280858,
            "crc": 2034635728,
            "state": "UPDATE",
            "md5": "39adc502f6bd189519eca22d76dd2723",
            "objectName": "KxxKLn",
            "generation": "1752639313230813",
            "uploadVersionId": 202050
        },
        {
            "id": 45558,
            "name": "img_dokan_free_login-pack-02-changed",
            "size": 325160,
            "crc": 1350745295,
            "state": "UPDATE",
            "md5": "e7c826f05e402e945b0c0627de3c8868",
            "objectName": "KqoBkH",
            "generation": "1752639313213033",
            "uploadVersionId": 202050
        },
        {
            "id": 45591,
            "name": "img_shop_item_thumb_shop-pack-25-0718-04",
            "size": 18755,
            "crc": 1351109624,
            "state": "UPDATE",
            "md5": "0eb4a1ba6040d8e8dddd79c52b79a36e",
            "objectName": "vBKMeM",
            "generation": "1752646092436679",
            "uploadVersionId": 202050
        }
    ],
    "resourceList": [],
    "urlFormat": "https://d2ilil7yh5oi1v.cloudfront.net/solis-{v}-{type}/{o}?generation={g}&alt=media"
}