{
    "revision": [
        661,
        654
    ],
    "assetBundleList": [
        {
            "id": 6140,
            "name": "mot_live_chr_cmn_spskill-sun-001-high_in",
            "size": 259520,
            "crc": 1856356846,
            "state": "UPDATE",
            "md5": "3f944eb9121fb960bd69cc593d428d91",
            "objectName": "holxDC",
            "generation": "1753149706497278",
            "uploadVersionId": 202050
        },
        {
            "id": 32265,
            "name": "mot_adv_chr_cmn_etc-010_in",
            "size": 139654,
            "crc": 3924844327,
            "state": "UPDATE",
            "md5": "119df71e567316ec94c262bb7fd9a47c",
            "objectName": "2Fw2tQ",
            "generation": "1753149610458898",
            "uploadVersionId": 202050
        },
        {
            "id": 34630,
            "name": "sud_vo_adv_bond_suz_01_06",
            "size": 1292564,
            "crc": 1320334244,
            "state": "UPDATE",
            "md5": "d3830dcf8d08407c0ef6836928c6d4f3",
            "objectName": "agjsnM",
            "generation": "1744288695938862",
            "uploadVersionId": 202050
        },
        {
            "id": 34631,
            "name": "sud_vo_adv_bond_skr_01_06",
            "size": 1124260,
            "crc": 3964773371,
            "state": "UPDATE",
            "md5": "52f5738248d5da3ee48e77ac4387097c",
            "objectName": "LlJsAr",
            "generation": "1744198891706785",
            "uploadVersionId": 202050
        },
        {
            "id": 34637,
            "name": "sud_vo_adv_bond_kor_01_06",
            "size": 1187548,
            "crc": 845265548,
            "state": "UPDATE",
            "md5": "a6cd48d32d5b7dc651700fb8bba7f2f5",
            "objectName": "ubs11E",
            "generation": "1737087275275650",
            "uploadVersionId": 202050
        },
        {
            "id": 34640,
            "name": "sud_vo_adv_bond_rei_01_06",
            "size": 972791,
            "crc": 2761798333,
            "state": "UPDATE",
            "md5": "19f66d64261f84c03b3d8c1d5d39a029",
            "objectName": "DSWWtH",
            "generation": "1744288695867581",
            "uploadVersionId": 202050
        },
        {
            "id": 40247,
            "name": "sud_vo_adv_bond_szk_01_06",
            "size": 1150475,
            "crc": 1737727018,
            "state": "UPDATE",
            "md5": "2ec22745d0547d5c85c96af4afb5e66d",
            "objectName": "88r8bG",
            "generation": "1737087275253383",
            "uploadVersionId": 202050
        },
        {
            "id": 40250,
            "name": "sud_vo_adv_bond_hrk_01_06",
            "size": 1288758,
            "crc": 206100583,
            "state": "UPDATE",
            "md5": "9d331823b2e9eb727f6beb10217b3544",
            "objectName": "3pvMbg",
            "generation": "1737087275265401",
            "uploadVersionId": 202050
        },
        {
            "id": 40254,
            "name": "sud_vo_adv_bond_kan_01_06",
            "size": 1160095,
            "crc": 1818623399,
            "state": "UPDATE",
            "md5": "a6b1ad9643ab4795c5c6a61c2cabe233",
            "objectName": "psbDMR",
            "generation": "1751512632354136",
            "uploadVersionId": 202050
        },
        {
            "id": 40260,
            "name": "sud_vo_adv_bond_yu_01_06",
            "size": 1326297,
            "crc": 4054560533,
            "state": "UPDATE",
            "md5": "3cb4b12c1f6be204e484f15acb400122",
            "objectName": "R6legO",
            "generation": "1744198891666920",
            "uploadVersionId": 202050
        },
        {
            "id": 40268,
            "name": "sud_vo_adv_bond_ski_01_06",
            "size": 1229546,
            "crc": 1765033415,
            "state": "UPDATE",
            "md5": "224038568d55611d0eba4f9448fec4a0",
            "objectName": "YV4pVB",
            "generation": "1744288695912005",
            "uploadVersionId": 202050
        },
        {
            "id": 40271,
            "name": "sud_vo_adv_bond_rio_01_06",
            "size": 1105108,
            "crc": 582137421,
            "state": "UPDATE",
            "md5": "62cbbc383642af9815569275632cd8e8",
            "objectName": "7yVKGF",
            "generation": "1737087275314286",
            "uploadVersionId": 202050
        },
        {
            "id": 40278,
            "name": "sud_vo_adv_bond_kkr_01_06",
            "size": 1071528,
            "crc": 4079995941,
            "state": "UPDATE",
            "md5": "4083c1723750eb5f1052a2c8f6473fb3",
            "objectName": "1VbfwE",
            "generation": "1744084198356487",
            "uploadVersionId": 202050
        },
        {
            "id": 40279,
            "name": "sud_vo_adv_bond_mei_01_06",
            "size": 1149876,
            "crc": 3448363338,
            "state": "UPDATE",
            "md5": "d8221d2a7c39dc08ed3c5c957845af1b",
            "objectName": "IGupMW",
            "generation": "1737087274960424",
            "uploadVersionId": 202050
        },
        {
            "id": 40285,
            "name": "sud_vo_adv_bond_smr_01_06",
            "size": 1242263,
            "crc": 3007246681,
            "state": "UPDATE",
            "md5": "0bf4ba5b0f331227c5eb52902d80d027",
            "objectName": "DlR309",
            "generation": "1737087274919251",
            "uploadVersionId": 202050
        },
        {
            "id": 42417,
            "name": "sud_vo_adv_bond_ngs_01_06",
            "size": 1205490,
            "crc": 170823416,
            "state": "UPDATE",
            "md5": "9a098cf6873410688eb6e9c7a6a99828",
            "objectName": "p6TIEe",
            "generation": "1754282373691876",
            "uploadVersionId": 202050
        },
        {
            "id": 42419,
            "name": "sud_vo_adv_bond_rui_01_06",
            "size": 1114231,
            "crc": 891555198,
            "state": "UPDATE",
            "md5": "2afd96dcca5b07f6d9175d55f81e22b9",
            "objectName": "MxpfYV",
            "generation": "1744198891706659",
            "uploadVersionId": 202050
        },
        {
            "id": 42420,
            "name": "sud_vo_adv_bond_ktn_01_06",
            "size": 1204547,
            "crc": 2066574466,
            "state": "UPDATE",
            "md5": "acfd93106408d1fb526ff00e36add02e",
            "objectName": "TbKojg",
            "generation": "1744117759842860",
            "uploadVersionId": 202050
        },
        {
            "id": 42429,
            "name": "sud_vo_adv_bond_aoi_01_06",
            "size": 1120678,
            "crc": 2784568531,
            "state": "UPDATE",
            "md5": "3d1147f2dafc17057fb16d2114cc3fb4",
            "objectName": "4d7l4l",
            "generation": "1744117758841280",
            "uploadVersionId": 202050
        },
        {
            "id": 42435,
            "name": "sud_vo_adv_bond_chs_01_06",
            "size": 1026679,
            "crc": 2547183527,
            "state": "UPDATE",
            "md5": "821e71e5649716c795382c910d633d86",
            "objectName": "YifeQ9",
            "generation": "1744620083855982",
            "uploadVersionId": 202050
        },
        {
            "id": 42439,
            "name": "sud_vo_adv_bond_mhk_01_06",
            "size": 993876,
            "crc": 260677633,
            "state": "UPDATE",
            "md5": "98408204b17fdc46d5e5867184e717dd",
            "objectName": "5Zf0ft",
            "generation": "1744288695848286",
            "uploadVersionId": 202050
        },
        {
            "id": 42440,
            "name": "sud_vo_adv_bond_ai_01_06",
            "size": 1036937,
            "crc": 3317252662,
            "state": "UPDATE",
            "md5": "d8abe029bbf147b6d68d9b69d372822c",
            "objectName": "Turkx7",
            "generation": "1748952011822500",
            "uploadVersionId": 202050
        },
        {
            "id": 46575,
            "name": "sud_se_adv_fall-02",
            "size": 72187,
            "crc": 3499799272,
            "state": "UPDATE",
            "md5": "aace162b57615cc70f01572c1e4f938a",
            "objectName": "bQQXiD",
            "generation": "1754656370246103",
            "uploadVersionId": 202050
        },
        {
            "id": 46577,
            "name": "sud_se_adv_stretch-01",
            "size": 324666,
            "crc": 43162880,
            "state": "UPDATE",
            "md5": "85929545c5fffffdc16c8d8ff44977a0",
            "objectName": "4cdBeY",
            "generation": "1754656370321862",
            "uploadVersionId": 202050
        },
        {
            "id": 46724,
            "name": "sud_se_adv_drill-01",
            "size": 403474,
            "crc": 1960883175,
            "state": "UPDATE",
            "md5": "480995fb632b00008d1c448e70ed8364",
            "objectName": "1DFCpN",
            "generation": "1756188807717885",
            "uploadVersionId": 202050
        },
        {
            "id": 46726,
            "name": "sud_se_adv_saw-01",
            "size": 1080899,
            "crc": 4108780812,
            "state": "UPDATE",
            "md5": "6df7ed5c3a2e1b69c158e32dd85e0df9",
            "objectName": "FMIc4V",
            "generation": "1756188807825892",
            "uploadVersionId": 202050
        },
        {
            "id": 46727,
            "name": "sud_se_adv_drill-02",
            "size": 198764,
            "crc": 902402116,
            "state": "UPDATE",
            "md5": "060d965d5b129001f8eb939aa76387f4",
            "objectName": "lqYrkm",
            "generation": "1756188807670853",
            "uploadVersionId": 202050
        },
        {
            "id": 46871,
            "name": "sud_se_adv_switch-02",
            "size": 82597,
            "crc": 3175582351,
            "state": "UPDATE",
            "md5": "cbff65ce64c42be542fb3d7088a5d9bf",
            "objectName": "BHrFgr",
            "generation": "1756447312258168",
            "uploadVersionId": 202050
        },
        {
            "id": 46908,
            "name": "sud_se_adv_cooking-06",
            "size": 12926765,
            "crc": 2530067615,
            "state": "UPDATE",
            "md5": "0b765693b9ff2bcb677f1d04317ca334",
            "objectName": "iaWj00",
            "generation": "1756805349600568",
            "uploadVersionId": 202050
        },
        {
            "id": 46909,
            "name": "sud_se_adv_cooking-07",
            "size": 802674,
            "crc": 948005402,
            "state": "UPDATE",
            "md5": "f3914254f85bce352a981cf6a29842b6",
            "objectName": "b4bXMn",
            "generation": "1756805348972750",
            "uploadVersionId": 202050
        },
        {
            "id": 47036,
            "name": "img_story_thumb_bond_hrk_01_06",
            "size": 201483,
            "crc": 468359686,
            "state": "UPDATE",
            "md5": "89b482d16839a494dc315ae677288214",
            "objectName": "nEv2kr",
            "generation": "1757404254717363",
            "uploadVersionId": 202050
        },
        {
            "id": 47037,
            "name": "img_story_thumb_bond_chs_01_06",
            "size": 235512,
            "crc": 2001984636,
            "state": "UPDATE",
            "md5": "fc1ef796c90130127c1e1ac2e834b083",
            "objectName": "yTyO5p",
            "generation": "1757404254744016",
            "uploadVersionId": 202050
        },
        {
            "id": 47038,
            "name": "img_story_thumb_bond_ngs_01_06",
            "size": 224906,
            "crc": 2942803823,
            "state": "UPDATE",
            "md5": "93e121120015fadcaf6f462895c80ef3",
            "objectName": "hPzRHn",
            "generation": "1757404254746855",
            "uploadVersionId": 202050
        },
        {
            "id": 47039,
            "name": "img_story_thumb_bond_rui_01_06",
            "size": 232478,
            "crc": 4222503919,
            "state": "UPDATE",
            "md5": "ecbaa39fbb0f3a649bc2eeb317ef909f",
            "objectName": "jP21fn",
            "generation": "1757404254746761",
            "uploadVersionId": 202050
        },
        {
            "id": 47040,
            "name": "img_story_thumb_bond_szk_01_06",
            "size": 230370,
            "crc": 2243048358,
            "state": "UPDATE",
            "md5": "bb5968bee6923be34f425f3dcfffe2d1",
            "objectName": "xQQPaA",
            "generation": "1757404254746825",
            "uploadVersionId": 202050
        },
        {
            "id": 47041,
            "name": "img_story_thumb_bond_mhk_01_06",
            "size": 205196,
            "crc": 3773017518,
            "state": "UPDATE",
            "md5": "11d356f502893ff7fec8744de06dce2a",
            "objectName": "D2MsVR",
            "generation": "1757404254746738",
            "uploadVersionId": 202050
        },
        {
            "id": 47043,
            "name": "img_story_thumb_bond_smr_01_06",
            "size": 223537,
            "crc": 616140089,
            "state": "UPDATE",
            "md5": "d4038585a1fa01ce2fee4ca52578acaa",
            "objectName": "OsekQD",
            "generation": "1757404254853565",
            "uploadVersionId": 202050
        },
        {
            "id": 47044,
            "name": "img_story_thumb_bond_mei_01_06",
            "size": 229692,
            "crc": 1151410557,
            "state": "UPDATE",
            "md5": "ca76d8e52f1ffe252f3aff12a9e0129a",
            "objectName": "gZckgq",
            "generation": "1757404254748213",
            "uploadVersionId": 202050
        },
        {
            "id": 47045,
            "name": "img_story_thumb_bond_rei_01_06",
            "size": 222179,
            "crc": 116259974,
            "state": "UPDATE",
            "md5": "553c6fcf117dbb0a9695a8872945e70d",
            "objectName": "eUpnLQ",
            "generation": "1757404255051505",
            "uploadVersionId": 202050
        },
        {
            "id": 47047,
            "name": "img_story_thumb_bond_ktn_01_06",
            "size": 230621,
            "crc": 3852323910,
            "state": "UPDATE",
            "md5": "ddca852d2f0b9141f93bac5bb67ea056",
            "objectName": "ARNsQo",
            "generation": "1757404255007672",
            "uploadVersionId": 202050
        },
        {
            "id": 47048,
            "name": "img_story_thumb_bond_yu_01_06",
            "size": 217726,
            "crc": 2010297098,
            "state": "UPDATE",
            "md5": "594c7ca9d96d8c1fdd1be5c845ac754d",
            "objectName": "aEgdK1",
            "generation": "1757404254667141",
            "uploadVersionId": 202050
        },
        {
            "id": 47052,
            "name": "img_story_thumb_bond_skr_01_06",
            "size": 224294,
            "crc": 143337312,
            "state": "UPDATE",
            "md5": "b45ea1beeed5da7acb06495b5999920f",
            "objectName": "e6I7VP",
            "generation": "1757410086106545",
            "uploadVersionId": 202050
        },
        {
            "id": 47053,
            "name": "img_story_thumb_bond_suz_01_06",
            "size": 222344,
            "crc": 1433137175,
            "state": "UPDATE",
            "md5": "a859c743faa422d5b06a1a58b31868b5",
            "objectName": "JPt2zk",
            "generation": "1757410085809957",
            "uploadVersionId": 202050
        },
        {
            "id": 47055,
            "name": "img_story_thumb_bond_kor_01_06",
            "size": 234237,
            "crc": 2417322806,
            "state": "UPDATE",
            "md5": "2c12f6e3e6cc6e19e6b861bccd9787ce",
            "objectName": "KOKvSs",
            "generation": "1757410085769484",
            "uploadVersionId": 202050
        },
        {
            "id": 47056,
            "name": "img_story_thumb_bond_ski_01_06",
            "size": 199306,
            "crc": 741889719,
            "state": "UPDATE",
            "md5": "434f2c64abcbda80788dd23ed2c8a21f",
            "objectName": "LWuqJT",
            "generation": "1757410085843422",
            "uploadVersionId": 202050
        },
        {
            "id": 47057,
            "name": "img_story_thumb_bond_kan_01_06",
            "size": 236240,
            "crc": 3626381021,
            "state": "UPDATE",
            "md5": "07cecb56772d1270a896c3a3e56ea40b",
            "objectName": "HqQWFE",
            "generation": "1757410085764467",
            "uploadVersionId": 202050
        },
        {
            "id": 47136,
            "name": "sud_se_adv_spray-01",
            "size": 325377,
            "crc": 3098787750,
            "state": "UPDATE",
            "md5": "239005a10616517e2f14cec3cb241b4d",
            "objectName": "N6U9mP",
            "generation": "1757592134850936",
            "uploadVersionId": 202050
        },
        {
            "id": 47138,
            "name": "sud_se_adv_petbottle-01",
            "size": 249322,
            "crc": 2796070172,
            "state": "UPDATE",
            "md5": "dbedf52a3650ab2264cfd39669833d35",
            "objectName": "EZWZjF",
            "generation": "1757592134927491",
            "uploadVersionId": 202050
        },
        {
            "id": 47139,
            "name": "sud_se_adv_water-05",
            "size": 42454,
            "crc": 3407874618,
            "state": "UPDATE",
            "md5": "02e93da7e91f3f44f1ad1d79aecd7c2b",
            "objectName": "FSk7V9",
            "generation": "1757592134659385",
            "uploadVersionId": 202050
        },
        {
            "id": 47303,
            "name": "img_story_thumb_bond_aoi_01_06",
            "size": 230164,
            "crc": 3875491824,
            "state": "UPDATE",
            "md5": "7cecdcc7cb17c81a98a45f2ebe6a496b",
            "objectName": "QT5Bd3",
            "generation": "1758093094506362",
            "uploadVersionId": 202050
        },
        {
            "id": 47304,
            "name": "img_story_thumb_bond_kkr_01_06",
            "size": 219161,
            "crc": 4210373990,
            "state": "UPDATE",
            "md5": "0c2d9456d31683e08076d105fe1bf4ef",
            "objectName": "b4jyor",
            "generation": "1758093094536254",
            "uploadVersionId": 202050
        },
        {
            "id": 47305,
            "name": "img_story_company_enjoy_episode-06",
            "size": 22384,
            "crc": 3510519062,
            "state": "UPDATE",
            "md5": "14a5d500e695dc6c78d802570543d104",
            "objectName": "gAXFOl",
            "generation": "1758093094375498",
            "uploadVersionId": 202050
        },
        {
            "id": 47307,
            "name": "img_story_thumb_bond_rio_01_06",
            "size": 226215,
            "crc": 140749378,
            "state": "UPDATE",
            "md5": "a1b32dc69438982ffe2baf8f5b1dbe54",
            "objectName": "hXwLBq",
            "generation": "1758093094507629",
            "uploadVersionId": 202050
        },
        {
            "id": 47309,
            "name": "img_story_thumb_bond_ai_01_06",
            "size": 227969,
            "crc": 3125460597,
            "state": "UPDATE",
            "md5": "28533f3c68d8728dadef9f7575435f5c",
            "objectName": "li8SaW",
            "generation": "1758093094722745",
            "uploadVersionId": 202050
        },
        {
            "id": 47460,
            "name": "img_item_thumb_enjoy-episode-06",
            "size": 22230,
            "crc": 1180839797,
            "state": "UPDATE",
            "md5": "a4238a6c8c4a1e017951b5b48b7ea853",
            "objectName": "ly7wlB",
            "generation": "1758866814333906",
            "uploadVersionId": 202050
        }
    ],
    "resourceList": [
        {
            "id": 1839,
            "name": "story-character-relations.json",
            "size": 216649,
            "state": "UPDATE",
            "md5": "6580a624167deafe82efa87e1bb9b0cf",
            "objectName": "iVKnyF",
            "generation": "1759287323832356",
            "uploadVersionId": 202050
        },
        {
            "id": 4160,
            "name": "adv_bond_skr_01_06.txt",
            "size": 170526,
            "state": "UPDATE",
            "md5": "f6a5bfdf4a84c1ea12eab0ca3843f8ac",
            "objectName": "esnrav",
            "generation": "1756176956330854",
            "uploadVersionId": 202050
        },
        {
            "id": 4161,
            "name": "adv_bond_kor_01_06.txt",
            "size": 190428,
            "state": "UPDATE",
            "md5": "ebc412a86a4171a82c16c7272af2e14a",
            "objectName": "NdEiP3",
            "generation": "1756102548080016",
            "uploadVersionId": 202050
        },
        {
            "id": 4162,
            "name": "adv_bond_ski_01_06.txt",
            "size": 180979,
            "state": "UPDATE",
            "md5": "f9077cea59308de1b46b2b7dadf2d5b2",
            "objectName": "QEo22V",
            "generation": "1756203127312721",
            "uploadVersionId": 202050
        },
        {
            "id": 4163,
            "name": "adv_bond_suz_01_06.txt",
            "size": 195958,
            "state": "UPDATE",
            "md5": "cbb845b8ef6ddcc1cca8a887f8d73ca0",
            "objectName": "rUfR8q",
            "generation": "1756203127318481",
            "uploadVersionId": 202050
        },
        {
            "id": 4166,
            "name": "adv_bond_kan_01_06.txt",
            "size": 196608,
            "state": "UPDATE",
            "md5": "21670ab5768cd5f4408203e983589008",
            "objectName": "lHrtTI",
            "generation": "1755775707779924",
            "uploadVersionId": 202050
        },
        {
            "id": 4225,
            "name": "adv_bond_ktn_01_06.txt",
            "size": 169835,
            "state": "UPDATE",
            "md5": "9570a14903aef190fd9ec61e3f075889",
            "objectName": "ZbqYjr",
            "generation": "1756458797815712",
            "uploadVersionId": 202050
        },
        {
            "id": 4226,
            "name": "adv_bond_chs_01_06.txt",
            "size": 165384,
            "state": "UPDATE",
            "md5": "15e1e068f953e4b835324e30ea01200e",
            "objectName": "fEEEtx",
            "generation": "1754419779915359",
            "uploadVersionId": 202050
        },
        {
            "id": 4227,
            "name": "adv_bond_ngs_01_06.txt",
            "size": 169767,
            "state": "UPDATE",
            "md5": "4bb8597f62d17d152547237048671171",
            "objectName": "duHnMA",
            "generation": "1756808432611607",
            "uploadVersionId": 202050
        },
        {
            "id": 4228,
            "name": "adv_bond_mhk_01_06.txt",
            "size": 179111,
            "state": "UPDATE",
            "md5": "a2c3d227027e573b962c6e4d2b3732a7",
            "objectName": "CYdKda",
            "generation": "1755775707787955",
            "uploadVersionId": 202050
        },
        {
            "id": 4229,
            "name": "adv_bond_mei_01_06.txt",
            "size": 181865,
            "state": "UPDATE",
            "md5": "d18e0e74d7a0022f9795e97f6787ed71",
            "objectName": "PoQWZg",
            "generation": "1756797948471348",
            "uploadVersionId": 202050
        },
        {
            "id": 4239,
            "name": "adv_bond_rei_01_06.txt",
            "size": 188098,
            "state": "UPDATE",
            "md5": "59f8109b22ac1759214a4befe214c6de",
            "objectName": "H89JbP",
            "generation": "1756797948361460",
            "uploadVersionId": 202050
        },
        {
            "id": 4242,
            "name": "adv_bond_szk_01_06.txt",
            "size": 198250,
            "state": "UPDATE",
            "md5": "02c591e48b2cd6a2bcece96b6e152d2d",
            "objectName": "kvb1fy",
            "generation": "1755283785568285",
            "uploadVersionId": 202050
        },
        {
            "id": 4245,
            "name": "adv_bond_hrk_01_06.txt",
            "size": 237986,
            "state": "UPDATE",
            "md5": "859425febe8598ac0bac3095de5f26ef",
            "objectName": "ULaGzQ",
            "generation": "1756797948501636",
            "uploadVersionId": 202050
        },
        {
            "id": 4246,
            "name": "adv_bond_yu_01_06.txt",
            "size": 214413,
            "state": "UPDATE",
            "md5": "79e6dfffd7e7a71c28ae129bdbec712f",
            "objectName": "DNUpUF",
            "generation": "1756797948555823",
            "uploadVersionId": 202050
        },
        {
            "id": 4249,
            "name": "adv_bond_rui_01_06.txt",
            "size": 199305,
            "state": "UPDATE",
            "md5": "e566ab745429f096dbc42492db82cb36",
            "objectName": "AVxR7P",
            "generation": "1756450917496235",
            "uploadVersionId": 202050
        },
        {
            "id": 4252,
            "name": "adv_bond_smr_01_06.txt",
            "size": 270616,
            "state": "UPDATE",
            "md5": "952e982602273f58dc1ca62aafbe0b29",
            "objectName": "URMVpf",
            "generation": "1756797948580205",
            "uploadVersionId": 202050
        },
        {
            "id": 4255,
            "name": "adv_bond_aoi_01_06.txt",
            "size": 229211,
            "state": "UPDATE",
            "md5": "134ed075027b023a8288b8fa3d178f63",
            "objectName": "5LzJUa",
            "generation": "1756320583116252",
            "uploadVersionId": 202050
        },
        {
            "id": 4260,
            "name": "adv_card_ski_53_03.txt",
            "size": 258141,
            "state": "UPDATE",
            "md5": "73f8da385f817ed0b184dba6461b9abc",
            "objectName": "JNg1hE",
            "generation": "1759287323836741",
            "uploadVersionId": 202050
        },
        {
            "id": 4297,
            "name": "adv_bond_kkr_01_06.txt",
            "size": 166050,
            "state": "UPDATE",
            "md5": "3d8f79d86e9cabe5187d5422c0eba567",
            "objectName": "FK6G8p",
            "generation": "1757398102494522",
            "uploadVersionId": 202050
        },
        {
            "id": 4328,
            "name": "adv_bond_ai_01_06.txt",
            "size": 182452,
            "state": "UPDATE",
            "md5": "f9af6ea6da50e4f1fbda3ae52e657532",
            "objectName": "SVCpd6",
            "generation": "1758511469649650",
            "uploadVersionId": 202050
        },
        {
            "id": 4332,
            "name": "adv_bond_rio_01_06.txt",
            "size": 192197,
            "state": "UPDATE",
            "md5": "6ca449393a86ff970657dc0a9f350899",
            "objectName": "fB2cio",
            "generation": "1759129137083851",
            "uploadVersionId": 202050
        }
    ],
    "urlFormat": "https://d2ilil7yh5oi1v.cloudfront.net/solis-{v}-{type}/{o}?generation={g}&alt=media"
}